GreenDeck/GsheetsTest.py
GreenDeck/__init__.py
GreenDeck_GsheetsTest-0.0.17.dist-info/LICENSE
GreenDeck_GsheetsTest-0.0.17.dist-info/METADATA
GreenDeck_GsheetsTest-0.0.17.dist-info/WHEEL
GreenDeck_GsheetsTest-0.0.17.dist-info/top_level.txt
GreenDeck_GsheetsTest-0.0.17.dist-info/RECORD
