Metadata-Version: 2.1
Name: GreenDeck-GsheetsTest
Version: 0.0.17
Summary: Greendeck Test to plot graph using gsheets
Home-page: https://github.com/snehkothari/GreenDeck_gsheets
Author: Sneh Kothari
Author-email: snehkothari1@gmail.com
License: UNKNOWN
Platform: UNKNOWN
Classifier: Programming Language :: Python :: 3
Classifier: License :: OSI Approved :: MIT License
Classifier: Operating System :: OS Independent
Requires-Python: >=3.7
Requires-Dist: matplotlib
Requires-Dist: pandas
Requires-Dist: gsheets
